byted_overpass_growth_diversion_algorithm_server/__init__.py
byted_overpass_growth_diversion_algorithm_server-0.0.1.dist-info/METADATA
byted_overpass_growth_diversion_algorithm_server-0.0.1.dist-info/WHEEL
byted_overpass_growth_diversion_algorithm_server-0.0.1.dist-info/top_level.txt
byted_overpass_growth_diversion_algorithm_server-0.0.1.dist-info/RECORD
